microsoft_agents/hosting/fastapi/__init__.py
microsoft_agents/hosting/fastapi/_start_agent_process.py
microsoft_agents/hosting/fastapi/agent_http_adapter.py
microsoft_agents/hosting/fastapi/channel_service_route_table.py
microsoft_agents/hosting/fastapi/cloud_adapter.py
microsoft_agents/hosting/fastapi/jwt_authorization_middleware.py
microsoft_agents/hosting/fastapi/app/__init__.py
microsoft_agents/hosting/fastapi/app/streaming/__init__.py
microsoft_agents/hosting/fastapi/app/streaming/citation.py
microsoft_agents/hosting/fastapi/app/streaming/citation_util.py
microsoft_agents/hosting/fastapi/app/streaming/streaming_response.py
microsoft_agents_hosting_fastapi-0.7.0.dist-info/licenses/LICENSE
microsoft_agents_hosting_fastapi-0.7.0.dist-info/METADATA
microsoft_agents_hosting_fastapi-0.7.0.dist-info/WHEEL
microsoft_agents_hosting_fastapi-0.7.0.dist-info/top_level.txt
microsoft_agents_hosting_fastapi-0.7.0.dist-info/RECORD
