Metadata-Version: 2.4
Name: microsoft-agents-hosting-fastapi
Version: 0.7.0
Summary: Integration library for Microsoft Agents with FastAPI
Author: Microsoft Corporation
License-Expression: MIT
Project-URL: Homepage, https://github.com/microsoft/Agents
Classifier: Programming Language :: Python :: 3
Classifier: Operating System :: OS Independent
Requires-Python: >=3.10
License-File: LICENSE
Requires-Dist: microsoft-agents-hosting-core==0.7.0
Requires-Dist: fastapi>=0.104.0
Dynamic: license-file
Dynamic: requires-dist
